datamemorys/__init__.py
datamemorys/core/__init__.py
datamemorys/core/common.py
datamemorys/datas/__init__.py
datamemorys/reports/__init__.py
datamemorys/utils/__init__.py
datamemorys-0.0.7.dist-info/METADATA
datamemorys-0.0.7.dist-info/WHEEL
datamemorys-0.0.7.dist-info/top_level.txt
datamemorys-0.0.7.dist-info/RECORD
