Metadata-Version: 2.1
Name: datamemorys
Version: 0.0.7
Summary: 数字记忆插件官方数据包
Home-page: https://www.zhihu.com/column/c_1410908597132423168
Author: lubupang
Author-email: lbl@rrftech.com
License: UNKNOWN
Platform: UNKNOWN
Requires-Dist: lac
Requires-Dist: pandas (==1.0.0)
